mkdocs_macros/__init__.py
mkdocs_macros/context.py
mkdocs_macros/errors.py
mkdocs_macros/macros_info.md
mkdocs_macros/plugin.py
mkdocs_macros/py.typed
mkdocs_macros/util.py
test/__init__.py
test/fixture.py
test/main_sample.py
test/module/__init__.py
test/module/main.py
test/module/test_site.py
test/module_dir/mymodule/__init__.py
test/new_syntax/main.py
test/no_module/main.py
test/null/__init__.py
test/null/test_site.py
test/opt_in/__init__.py
test/opt_in/test_site.py
test/opt_in/__pycache__/new_syntax/main.py
test/opt_out/__init__.py
test/opt_out/test_site.py
test/opt_out/__pycache__/new_syntax/main.py
test/plugin_d2/__init__.py
test/plugin_d2/test_t2.py
test/register_macros/__init__.py
test/register_macros/hooks.py
test/register_macros/test_doc.py
test/simple/__init__.py
test/simple/main_old.py
test/simple/test_site.py
mkdocs_macros_plugin-1.3.7.dist-info/LICENSE.md
mkdocs_macros_plugin-1.3.7.dist-info/METADATA
mkdocs_macros_plugin-1.3.7.dist-info/WHEEL
mkdocs_macros_plugin-1.3.7.dist-info/entry_points.txt
mkdocs_macros_plugin-1.3.7.dist-info/top_level.txt
mkdocs_macros_plugin-1.3.7.dist-info/RECORD
