Metadata-Version: 2.1
Name: mkdocs-macros-plugin
Version: 1.3.7
Summary: Unleash the power of MkDocs with macros and variables
Author-email: Laurent Franceschetti <info@settlenext.com>
License: MIT
Project-URL: Homepage, https://github.com/fralau/mkdocs_macros_plugin
Keywords: macros,markdown,mkdocs,python
Classifier: Development Status :: 5 - Production/Stable
Classifier: Intended Audience :: Developers
Classifier: Intended Audience :: Information Technology
Classifier: License :: OSI Approved :: MIT License
Classifier: Programming Language :: Python
Classifier: Programming Language :: Python :: 3 :: Only
Classifier: Programming Language :: Python :: 3.5
Requires-Python: >=3.8
License-File: LICENSE.md
Requires-Dist: hjson
Requires-Dist: jinja2
Requires-Dist: mkdocs>=0.17
Requires-Dist: packaging
Requires-Dist: pathspec
Requires-Dist: python-dateutil
Requires-Dist: pyyaml
Requires-Dist: super-collections
Requires-Dist: termcolor
Provides-Extra: test
Requires-Dist: mkdocs-include-markdown-plugin; extra == "test"
Requires-Dist: mkdocs-macros-test; extra == "test"
Requires-Dist: mkdocs-material>=6.2; extra == "test"
Requires-Dist: mkdocs-test; extra == "test"
Requires-Dist: mkdocs-d2-plugin; extra == "test"
